odoo8_addon_l10n_es_partner-8.0.1.5.3-py2.7-nspkg.pth
odoo8_addon_l10n_es_partner-8.0.1.5.3.dist-info/DESCRIPTION.rst
odoo8_addon_l10n_es_partner-8.0.1.5.3.dist-info/METADATA
odoo8_addon_l10n_es_partner-8.0.1.5.3.dist-info/RECORD
odoo8_addon_l10n_es_partner-8.0.1.5.3.dist-info/WHEEL
odoo8_addon_l10n_es_partner-8.0.1.5.3.dist-info/metadata.json
odoo8_addon_l10n_es_partner-8.0.1.5.3.dist-info/namespace_packages.txt
odoo8_addon_l10n_es_partner-8.0.1.5.3.dist-info/top_level.txt
odoo_addons/l10n_es_partner/README.rst
odoo_addons/l10n_es_partner/__init__.py
odoo_addons/l10n_es_partner/__openerp__.py
odoo_addons/l10n_es_partner/data/l10n_es_partner_data.xml
odoo_addons/l10n_es_partner/gen_src/README.rst
odoo_addons/l10n_es_partner/gen_src/__init__.py
odoo_addons/l10n_es_partner/gen_src/bics.xls
odoo_addons/l10n_es_partner/gen_src/gen_data_banks.py
odoo_addons/l10n_es_partner/i18n/bg.po
odoo_addons/l10n_es_partner/i18n/ca.po
odoo_addons/l10n_es_partner/i18n/cs.po
odoo_addons/l10n_es_partner/i18n/es.po
odoo_addons/l10n_es_partner/i18n/es_CO.po
odoo_addons/l10n_es_partner/i18n/es_CR.po
odoo_addons/l10n_es_partner/i18n/eu.po
odoo_addons/l10n_es_partner/i18n/fr.po
odoo_addons/l10n_es_partner/i18n/gl.po
odoo_addons/l10n_es_partner/i18n/hr.po
odoo_addons/l10n_es_partner/i18n/l10n_es_partner.pot
odoo_addons/l10n_es_partner/i18n/nl.po
odoo_addons/l10n_es_partner/i18n/pl.po
odoo_addons/l10n_es_partner/i18n/pt.po
odoo_addons/l10n_es_partner/i18n/pt_BR.po
odoo_addons/l10n_es_partner/i18n/ru.po
odoo_addons/l10n_es_partner/i18n/sl.po
odoo_addons/l10n_es_partner/i18n/sv.po
odoo_addons/l10n_es_partner/i18n/tr.po
odoo_addons/l10n_es_partner/i18n/vi.po
odoo_addons/l10n_es_partner/migrations/8.0.1.3/pre-migration.py
odoo_addons/l10n_es_partner/migrations/8.0.1.4/pre-migration.py
odoo_addons/l10n_es_partner/models/__init__.py
odoo_addons/l10n_es_partner/models/l10n_es_partner.py
odoo_addons/l10n_es_partner/static/description/bank.svg
odoo_addons/l10n_es_partner/static/description/icon.png
odoo_addons/l10n_es_partner/tests/__init__.py
odoo_addons/l10n_es_partner/tests/test_l10n_es_partner.py
odoo_addons/l10n_es_partner/views/l10n_es_partner_view.xml
odoo_addons/l10n_es_partner/wizard/__init__.py
odoo_addons/l10n_es_partner/wizard/data_banks.xml
odoo_addons/l10n_es_partner/wizard/l10n_es_partner_wizard.py
odoo_addons/l10n_es_partner/wizard/l10n_es_partner_wizard.xml
